Workbook

Sheet SEC_Comm
B2: Define Commodities
B4: ~FI_Comm
B5: Csets | C5: CommName | D5: CommDesc | E5: Unit | F5: LimType | G5: CTSLvl | H5: PeakTS | I5: Ctype
B6: \I: Commodity Set | C6: Commodity Name | D6: Commodity Description | E6: Unit | F6: Sense of Balance Equation | G6: TimeSlice Level | H6: Peak Monitoring | I6: Electricity Indicator (for CHPs)
B7: NRG | C7: SOLID | D7: Solid Fuels | E7: PJ
B8: NRG | C8: CRUDE_OIL | D8: Oil | E8: PJ
B9: NRG | C9: OILGAS | D9: Syngas_Res | E9: PJ
B10: NRG | C10: DIESEL | D10: Diesel | E10: PJ
B11: NRG | C11: GASOLINE | D11: Gasoline | E11: PJ
B12: NRG | C12: OGL | D12: OilGasLiquid | E12: PJ
B13: NRG | C13: FUEL_OIL | D13: FUEL_OIL | E13: PJ
B14: NRG | C14: Jet_Fuel | D14: Jet Fuel | E14: PJ
B15: NRG | C15: Lubricants | D15: Lubricants | E15: PJ
B16: NRG | C16: Bitumen | D16: Bitumen | E16: PJ
B17: NRG | C17: Ethy_and_Prop | D17: Ethy and Prop | E17: PJ
B18: NRG | C18: NLG | D18: Natural Liquid Gas | E18: PJ
... B28: NRG | C28: OTHER | D28: OTHER | E28: PJ
B33: Available Commodity Sets
B34: NRG | C34: Energy
B35: ENV | C35: Emission
B36: DEM | C36: Demand
B37: MAT | C37: Material
B38: FIN | C38: Financial

Sheet sec_processes
B2: Define Processes
B4: ~FI_Process
B5: Sets | C5: Region | D5: TechName | E5: TechDesc | F5: Tact | G5: Tcap | H5: Tslvl | I5: PrimaryCG | J5: Vintage
B6: \I: Process Set | C6: Region Name | D6: Technology Name | E6: Technology Description | F6: Activity Unit | G6: Capacity Unit | H6: TimeSlice Level | I6: Primary Commodity Group | J6: Vintage Tracking
B7: IMP | C7: SAR | D7: IMP_SOLID | E7: Solid Input Supply | F7: PJ | H7: ANNUAL
B8: IMP | C8: SAR | D8: IMP_CRUDE_OIL | E8: Oil input Supply | F8: PJ | H8: ANNUAL
B9: IMP | C9: SAR | D9: IMP_BIOMASS | E9: Biomass input Supply | F9: PJ | H9: ANNUAL | L9: <- supply of biomass from two different sources
B10: IMP | C10: SAR | D10: IMP_NLG | E10: Natural Liquid Gas | F10: PJ | H10: ANNUAL
B11: \I:
B12: MIN | C12: SAR | D12: MIN_OILGAS | E12: Industrial synthesis gas derived from oil refinery by-products | F12: PJ | H12: ANNUAL
B13: MIN | C13: SAR | D13: MIN_SOLAR | E13: Solar | F13: PJ | H13: ANNUAL
B14: MIN | C14: SAR | D14: MIN_BIOMASS | E14: Local Biomass | F14: PJ | H14: ANNUAL
B15: MIN | C15: SAR | D15: MIN_WIND_ON | E15: Wind | F15: PJ | H15: ANNUAL
B16: MIN | C16: SAR | D16: MIN_BIOGAS_AGR | E16: Biogas Production | F16: PJ | H16: ANNUAL
B17: MIN | C17: SAR | D17: MIN_HIDROGEN | E17: Hidrogen Supply | F17: PJ | H17: ANNUAL
B21: Available Process Sets
B22: ELE | C22: Power Plant (Electricity Only)
B23: CHP | C23: Combined Heat & Power Plant
B24: STG | C24: Timeslice Storage
B25: PRE | C25: Generic Process
B26: DMD | C26: Demand Process | D26: Demand Type Commodity at Output
B27: IMP | C27: Import | D27: Commodity only at Output
B28: EXP | C28: Eksport | D28: Commodity only at Input
B29: MIN | C29: Mining | D29: Commodity only at Output
B30: HPL | C30: Heat Only Plant

Sheet MIN_IMP
B2: Primary Energy Carriers Extraction | N2: Very Long Table
B4: ~FI_T
B5: TechName | C5: * TechDesc | D5: Comm-OUT | E5: COST | F5: ACT_BND~UP | G5: ACT_BND~FX | H5: ACT_BND~LO | N5: TechName | O5: * TechDesc | P5: Comm-OUT | Q5: COST~2020 | R5: COST~2025 | S5: COST~2030 | T5: COST~2035 | U5: COST~2040 | V5: COST~2045 | W5: COST~2050 | X5: ACT_BND~UP~2020 | Y5: ACT_BND~UP~2025 | Z5: ACT_BND~UP~2030 | AA5: ACT_BND~UP~2035 | AB5: ACT_BND~UP~2040 | AC5: ACT_BND~UP~2045 | AD5: ACT_BND~UP~2050 | AE5: ACT_BND~LO~2020 | AF5: ACT_BND~LO~2025 | AG5: ACT_BND~LO~2030 | AH5: ACT_BND~LO~2035 | AI5: ACT_BND~LO~2040 | AJ5: ACT_BND~LO~2045 | AK5: ACT_BND~LO~2050
B6: \I: Technology Name | C6: Technology Description | D6: Output Commodity | E6: Extraction Cost [MEUR/PJ] | F6: Annual Extraction Upper Bound [PJ/a] | G6: Annual Extraction Fixed Bound [PJ/a] | H6: Annual Extraction Lower Bound [PJ/a] | N6: \I: Technology Name | O6: Technology Description | P6: Output Commodity | Q6: Extraction Cost [MEURPJ] | X6: Annual Extraction Upper Bound [PJ/a] | AE6: Annual Extraction Lower Bound [PJ/a]
B7: =sec_processes!D7 -> IMP_SOLID | C7: =sec_processes!E7 -> Solid Input Supply | D7: =SEC_Comm!C7 -> SOLID | E7: 5.72
B8: =sec_processes!D8 -> IMP_CRUDE_OIL | C8: =sec_processes!E8 -> Oil input Supply | D8: =SEC_Comm!C8 -> CRUDE_OIL | E8: 13.33
B9: =sec_processes!D10 -> IMP_NLG | C9: Natural Liquid Gas | D9: =SEC_Comm!C18 -> NLG | E9: 12.52
B10: =sec_processes!D9 -> IMP_BIOMASS | C10: =sec_processes!E9 -> Biomass input Supply | D10: =SEC_Comm!C19 -> BIOMASS | E10: 21
B11: =sec_processes!D12 -> MIN_OILGAS | C11: =sec_processes!E12 -> Industrial synthesis gas derived from oil refinery by-products | D11: =SEC_Comm!C9 -> OILGAS | E11: 15
B12: =sec_processes!D13 -> MIN_SOLAR | C12: =sec_processes!E13 -> Solar | D12: =SEC_Comm!C25 -> SOLAR | E12: 0.01
B13: =sec_processes!D15 -> MIN_WIND_ON | C13: =sec_processes!E15 -> Wind | D13: =SEC_Comm!C23 -> WIND-ON | E13: 0.01
B14: MIN_HIDRO | C14: Water | D14: =SEC_Comm!C20 -> HIDRO | E14: 0.01
B15: =sec_processes!D16 -> MIN_BIOGAS_AGR | C15: =sec_processes!E16 -> Biogas Production | D15: =SEC_Comm!C24 -> BIOGAS | E15: 27 | F15: 5.12
B16: =sec_processes!D14 -> MIN_BIOMASS | C16: =sec_processes!E14 -> Local Biomass | D16: =SEC_Comm!C19 -> BIOMASS | E16: 19 | F16: 5.08
N19: =#REF! -> #REF! | O19: =#REF! -> #REF! | P19: =#REF! -> #REF! | Q19: 0.001 | R19: 0.001 | S19: 0.001 | T19: 0.001 | U19: 0.001 | V19: 0.001 | W19: 0.001
AA21: ?????????
B22: Alternative syntax with LimType Attribute
B28: -> Example of assignment of attribute values in all model years (cumbersome to maintain)
B30: <- Only baseline price here. Actual forecast of fuel prices in future years is in the scenario file "FUEL_PRICE_PROJ".
